bandcamp/__init__.py
bandcamp/__main__.py
bandcamp/app/__init__.py
bandcamp/app/player.py
bandcamp/app/tui.py
bandcamp/web/__init__.py
bandcamp/web/base.py
bandcamp/web/elements.py
bandcamp/web/locators.py
bandcamp/web/pages.py
pycamp-0.1.1.dist-info/METADATA
pycamp-0.1.1.dist-info/WHEEL
pycamp-0.1.1.dist-info/entry_points.txt
pycamp-0.1.1.dist-info/top_level.txt
pycamp-0.1.1.dist-info/RECORD
